{
    "作者": "Aries",
    "站名": "https://www.fullhd.xxx/zh/",
    "请求头": "User-Agent$MOBILE_UA",
    "编码": "UTF-8",
    "主页url": "https://www.fullhd.xxx/zh/latest-updates/",
    "首页": "120",
    "起始页": "1",
    "分类url": "https://www.fullhd.xxx/zh/networks/{cateId}/{catePg}/;;z",
    "分类": "Brazzers$brazzers-com#MYLF$mylf-com#BLACKED$blacked#Team Skeet$teamskeet-com#Bangbros$bangbros#Nubiles Porn$nubiles-porn-com#Adult Time$adult-time#TUSHY$tushy-com#Private$private#Woodman Casting$woodman-casting#Naughty America$naughtyamerica-com#Mom Lover$mom-lover#Reality Kings$rk-com#MOFOS$mofos-com",
    "数组": "class=\"item\">&&item-info",
    "标题": "title=\"&&\"",
    "图片": "data-src=\"&&\"",
    "副标题": "duration\">&&</div>",
    "链接": "href=\"&&\""
}
